adc_socketx/__init__.py
adc_socketx/commands.py
adc_socketx/config.py
adc_socketx/data_models.py
adc_socketx/main.py
adc_socketx-0.1.1.dist-info/LICENSE
adc_socketx-0.1.1.dist-info/METADATA
adc_socketx-0.1.1.dist-info/WHEEL
adc_socketx-0.1.1.dist-info/entry_points.txt
adc_socketx-0.1.1.dist-info/RECORD
