Metadata-Version: 2.1
Name: adc-socketx
Version: 0.1.1
Summary: ADC socket data eXchange
License: GTLAB Diagnostic, LLC
Author: Pavel Russu
Author-email: pavlucho@gmail.com
Requires-Python: >=3.10,<4.0
Classifier: License :: Other/Proprietary License
Classifier: Programming Language :: Python :: 3
Classifier: Programming Language :: Python :: 3.10
Classifier: Programming Language :: Python :: 3.11
Requires-Dist: numpy (>=1.24.2,<2.0.0)
Requires-Dist: soundfile (>=0.12.1,<0.13.0)
Requires-Dist: typer[all] (>=0.7.0,<0.8.0)
